aliyunsdklto/__init__.py
aliyunsdklto/request/__init__.py
aliyunsdklto/request/v20210707/AddBaaSAntChainBizChainRequest.py
aliyunsdklto/request/v20210707/AddBaaSFabricBizChainRequest.py
aliyunsdklto/request/v20210707/AddBsnFabricBizChainRequest.py
aliyunsdklto/request/v20210707/AddDeviceGroupRequest.py
aliyunsdklto/request/v20210707/AddMemberRequest.py
aliyunsdklto/request/v20210707/AddPrivacyRuleRequest.py
aliyunsdklto/request/v20210707/AddRouteRuleRequest.py
aliyunsdklto/request/v20210707/AgreeMemberAccessRequest.py
aliyunsdklto/request/v20210707/AuthorizeBaaSRequest.py
aliyunsdklto/request/v20210707/AuthorizeDeviceGroupBizChainRequest.py
aliyunsdklto/request/v20210707/AuthorizeMemberBizChainRequest.py
aliyunsdklto/request/v20210707/DeletePrivacyRuleRequest.py
aliyunsdklto/request/v20210707/DeleteRouteRuleRequest.py
aliyunsdklto/request/v20210707/DeniedMemberAccessRequest.py
aliyunsdklto/request/v20210707/DescribeAccountRoleRequest.py
aliyunsdklto/request/v20210707/DescribeAdminInfoRequest.py
aliyunsdklto/request/v20210707/DescribeBizChainStatInfoRequest.py
aliyunsdklto/request/v20210707/DescribeDashboardApiInfoRequest.py
aliyunsdklto/request/v20210707/DescribeDashboardBaseInfoRequest.py
aliyunsdklto/request/v20210707/DescribeDashboardDeviceInfoRequest.py
aliyunsdklto/request/v20210707/DescribeDashboardMemberApiInfoRequest.py
aliyunsdklto/request/v20210707/DescribeDashboardMemberDeviceInfoRequest.py
aliyunsdklto/request/v20210707/DescribeDeviceInfoRequest.py
aliyunsdklto/request/v20210707/DescribeEdgeStatInfoRequest.py
aliyunsdklto/request/v20210707/DescribeMemberBizChainStatInfoRequest.py
aliyunsdklto/request/v20210707/DescribeMemberStatInfoRequest.py
aliyunsdklto/request/v20210707/DescribeMemberTotalStatInfoRequest.py
aliyunsdklto/request/v20210707/DescribePackgeInfoRequest.py
aliyunsdklto/request/v20210707/DescribeStatDeviceInfoRequest.py
aliyunsdklto/request/v20210707/DescribeStatMemberDeviceInfoRequest.py
aliyun_python_sdk_lto-1.0.0.dist-info/LICENSE
aliyun_python_sdk_lto-1.0.0.dist-info/METADATA
aliyun_python_sdk_lto-1.0.0.dist-info/WHEEL
aliyun_python_sdk_lto-1.0.0.dist-info/top_level.txt
aliyun_python_sdk_lto-1.0.0.dist-info/RECORD
